zmqcs/__init__.py
zmqcs/logs.py
zmqcs/client/__init__.py
zmqcs/client/callbacks.py
zmqcs/client/client.py
zmqcs/client/stats.py
zmqcs/common/__init__.py
zmqcs/common/defaults.py
zmqcs/common/message.py
zmqcs/server/AsyncStats.py
zmqcs/server/__init__.py
zmqcs/server/server.py
zmqcs-0.1.1.dist-info/LICENSE.txt
zmqcs-0.1.1.dist-info/METADATA
zmqcs-0.1.1.dist-info/WHEEL
zmqcs-0.1.1.dist-info/top_level.txt
zmqcs-0.1.1.dist-info/RECORD
