Metadata-Version: 2.1
Name: zmqcs
Version: 0.1.1
Summary: Client Server implementation made with zmq
Home-page: https://github.com/IFAEControl/zmqCS
Author: Otger Ballester
Author-email: ifae-control@ifae.es
License: CC0 1.0 Universal
Platform: UNKNOWN
Classifier: Development Status :: 4 - Beta
Classifier: Programming Language :: Python :: 3
Provides: zmqcs
Requires-Python: >=3
License-File: LICENSE.txt
Requires-Dist: pyzmq
